wigli/__init__.py
wigli/__main__.py
wigli/_wigli_argparser.py
wigli/_wigli_bots.py
wigli/_wigli_cli.py
wigli/_wigli_data.py
wigli/_wigli_plugins.py
wigli/_wigli_testutils.py
wigli/_wigli_tools.py
wigli/_wigli_version.py
wigli-0.1.9.dist-info/entry_points.txt
wigli-0.1.9.dist-info/LICENSE
wigli-0.1.9.dist-info/METADATA
wigli-0.1.9.dist-info/WHEEL
wigli-0.1.9.dist-info/RECORD
