Metadata-Version: 2.1
Name: wigli
Version: 0.1.9
Summary: Powerful ChatGPT wrapper adds extensible botswarms for web search, coding, and more.
License: MIT
Author: Douglas Graham
Author-email: doug.n.graham@gmail.com
Requires-Python: >=3.7,<4.0
Classifier: License :: OSI Approved :: MIT License
Classifier: Programming Language :: Python :: 3
Classifier: Programming Language :: Python :: 3.7
Classifier: Programming Language :: Python :: 3.8
Classifier: Programming Language :: Python :: 3.9
Classifier: Programming Language :: Python :: 3.10
Classifier: Programming Language :: Python :: 3.11
Requires-Dist: appdirs
Requires-Dist: beautifulsoup4
Requires-Dist: duckduckgo_search
Requires-Dist: jsonpickle
Requires-Dist: openai
Requires-Dist: python-dotenv
Requires-Dist: tiktoken
Requires-Dist: unicode_slugify
Requires-Dist: urllib3
